<annotation>
	<folder>train</folder>
	<filename>armas (1761).jpg</filename>
	<path>D:\LEAR\models\research\object_detection\images\train\armas (1761).jpg</path>
	<source>
		<database>Unknown</database>
	</source>
	<size>
		<width>376</width>
		<height>472</height>
		<depth>3</depth>
	</size>
	<segmented>0</segmented>
	<object>
		<name>Arma</name>
		<pose>Unspecified</pose>
		<truncated>0</truncated>
		<difficult>0</difficult>
		<bndbox>
			<xmin>141</xmin>
			<ymin>269</ymin>
			<xmax>333</xmax>
			<ymax>375</ymax>
		</bndbox>
	</object>
</annotation>
